{"cameraMode":{"drawMode":0,"name":"Shaded","section":"Shading Mode"},"sceneLighting":false,"audioPlay":false,"sceneViewState":{"m_AlwaysRefresh":false,"showFog":true,"showSkybox":true,"showFlares":true,"showImageEffects":true,"showParticleSystems":true,"showVisualEffectGraphs":true,"m_FxEnabled":false},"in2DMode":false,"pivot":{"x":-15.476948738098145,"y":3.161334991455078,"z":-1.319375991821289},"rotation":{"x":-0.058235492557287219,"y":-0.9164021015167236,"z":0.3686770498752594,"w":-0.14468374848365785},"size":13.349283218383789,"orthographic":false}